MANIFEST.in
README
README.md
setup.py
polycircles/__init__.py
polycircles/polycircles.py
polycircles.egg-info/PKG-INFO
polycircles.egg-info/SOURCES.txt
polycircles.egg-info/dependency_links.txt
polycircles.egg-info/not-zip-safe
polycircles.egg-info/requires.txt
polycircles.egg-info/top_level.txt